<blocks app="Snap! 7, https://snap.berkeley.edu" version="2"><block-definition s="bitwise not %&apos;a&apos;" type="reporter" category="operators"><header></header><code></code><translations></translations><inputs><input type="%n"></input></inputs><script><block s="doReport"><block s="reportApplyExtension"><l>bit_not(a)</l><list><block var="a"/></list></block></block></script></block-definition><block-definition s="bitwise %&apos;a&apos; and %&apos;b&apos;" type="reporter" category="operators"><header></header><code></code><translations></translations><inputs><input type="%n"></input><input type="%n"></input></inputs><script><block s="doReport"><block s="reportApplyExtension"><l>bit_and(a, b)</l><list><block var="a"/><block var="b"/></list></block></block></script></block-definition><block-definition s="bitwise %&apos;a&apos; or %&apos;b&apos;" type="reporter" category="operators"><header></header><code></code><translations></translations><inputs><input type="%n"></input><input type="%n"></input></inputs><script><block s="doReport"><block s="reportApplyExtension"><l>bit_or(a, b)</l><list><block var="a"/><block var="b"/></list></block></block></script></block-definition><block-definition s="bitwise %&apos;a&apos; xor %&apos;b&apos;" type="reporter" category="operators"><header></header><code></code><translations></translations><inputs><input type="%n"></input><input type="%n"></input></inputs><script><block s="doReport"><block s="reportApplyExtension"><l>bit_xor(a, b)</l><list><block var="a"/><block var="b"/></list></block></block></script></block-definition><block-definition s="bitwise left shift %&apos;a&apos; by %&apos;b&apos; bytes" type="reporter" category="operators"><header></header><code></code><translations></translations><inputs><input type="%n"></input><input type="%n"></input></inputs><script><block s="doReport"><block s="reportApplyExtension"><l>bit_left_shift(a, b)</l><list><block var="a"/><block var="b"/></list></block></block></script></block-definition><block-definition s="bitwise right shift %&apos;a&apos; by %&apos;b&apos; bytes" type="reporter" category="operators"><header></header><code></code><translations></translations><inputs><input type="%n"></input><input type="%n"></input></inputs><script><block s="doReport"><block s="reportApplyExtension"><l>bit_right_shift(a, b)</l><list><block var="a"/><block var="b"/></list></block></block></script></block-definition><block-definition s="bitwise unsigned right shift %&apos;a&apos; by %&apos;b&apos; bytes" type="reporter" category="operators"><header></header><code></code><translations></translations><inputs><input type="%n"></input><input type="%n"></input></inputs><script><block s="doReport"><block s="reportApplyExtension"><l>bit_unsigned_right_shift(a, b)</l><list><block var="a"/><block var="b"/></list></block></block></script></block-definition></blocks>